{
    "Математика": [
        {
            "title": "Факториал",
            "id": "factorial",
            "engineCompatible": true
        },
        {
            "title": "Квадратный корень",
            "id": "square-root",
            "engineCompatible": true
        },
        {
            "title": "Простое сложение",
            "id": "simple-addition",
            "engineCompatible": true
        },
        {
            "title": "Таблица умножения",
            "id": "multiplication",
            "engineCompatible": true
        }
    ],
    "Геометрия": [
        {
            "title": "Теорема Пифагора",
            "id": "pythagorean-theorem"
        },
        {
            "title": "Геометрические фигуры",
            "id": "geometric-figures",
            "url": "/lera_game/lessons/geometry/geometric_figures.html"
        }
    ],
    "Русский язык": [
        {
            "title": "Орфография: Гласные",
            "id": "spelling-vowels",
            "url": "/lera_game/lessons/russian/spelling_game.html"
        }
    ]
}